matomo_api_tracking/__init__.py
matomo_api_tracking/apps.py
matomo_api_tracking/middleware.py
matomo_api_tracking/tasks.py
matomo_api_tracking/test_runner.py
matomo_api_tracking/tests.py
matomo_api_tracking/utils.py
django_matomo_api_tracking-0.2.0.dist-info/METADATA
django_matomo_api_tracking-0.2.0.dist-info/WHEEL
django_matomo_api_tracking-0.2.0.dist-info/licenses/LICENSE
django_matomo_api_tracking-0.2.0.dist-info/RECORD
