Metadata-Version: 2.4
Name: django-matomo-api-tracking
Version: 0.2.0
Summary: Django app to track webtraffic serverside with Matomo API
License-Expression: BSD-4-Clause
License-File: LICENSE
Author: Adrian Altenhoff
Author-email: adrian.altenhoff@inf.ethz.ch
Requires-Python: >=3.10, <3.13
Classifier: Programming Language :: Python :: 3
Classifier: Programming Language :: Python :: 3.10
Classifier: Programming Language :: Python :: 3.11
Classifier: Programming Language :: Python :: 3.12
Provides-Extra: dev
Requires-Dist: beautifulsoup4 (>=4.12.0,<5.0)
Requires-Dist: celery (>4.0.0,<6.0)
Requires-Dist: django (>=2.2.5,<6.0)
Requires-Dist: flake8 (>5.0.0) ; extra == "dev"
Requires-Dist: requests (>=2.28.2,<3.0)
Requires-Dist: responses (>0.23.1,<1.0) ; extra == "dev"
